crmv2_auth_lib/__init__.py
crmv2_auth_lib/auth.py
crmv2_auth_lib/percobaan.py
crmv2_auth_lib old/__init__.py
crmv2_auth_lib old/auth.py
crmv2_auth_lib old/percobaan.py
test/__init__.py
test/test_function.py
crmv2_auth_lib-0.2.5.dist-info/METADATA
crmv2_auth_lib-0.2.5.dist-info/WHEEL
crmv2_auth_lib-0.2.5.dist-info/top_level.txt
crmv2_auth_lib-0.2.5.dist-info/RECORD
