Metadata-Version: 2.1
Name: crmv2-auth-lib
Version: 0.2.5
Summary: Auth Library CRMV2 Staging
Author: mrizkyff
License: MIT
Requires-Dist: pyjwt
